{
  "button": [
  {
    "name": "预定",
    "sub_button": [
    {
      "type": "view",
      "name": "周边旅游",
      "url": "http://foo.bar.com",
      "key": "AROUND"
    },
    {
      "type": "view",
      "name": "国内旅游",
      "url": "http://foo.bar.com",
      "key": "DEMESTIC"
    },
    {
      "type": "view",
      "name": "处境旅游",
      "url": "http://foo.bar.com",
      "key": "ABROAD"
    }]
  },
  {
    "name": "目的地",
    "sub_button": [
    {
      "type": "view",
      "name": "马尔代夫",
      "url": "http://foo.bar.com",
      "key": "MALDIVES"
    },
    {
      "type": "view",
      "name": "欧洲",
      "url": "http://foo.bar.com",
      "key": "EUROPE"
    },
    {
      "type": "view",
      "name": "泰国",
      "url": "http://foo.bar.com",
      "key": "THAILAND"
    },
    {
      "type": "view",
      "name": "香港",
      "url": "http://foo.bar.com",
      "key": "HONGKONG"
    }]
  },
  {
    "name": "服务",
    "sub_button": [
    {
      "type": "click",
      "name": "搜索产品",
      "key": "SEARCH"
    },
    {
      "type": "click",
      "name": "注册赠抵用券",
      "key": "REGISTER"
    },
    {
      "type": "click",
      "name": "订单查询",
      "key": "ORDERS"
    }]
  }]
}